CHANGELOG.txt
LICENSE.txt
MANIFEST.in
README.md
setup.py
fastfile/__init__.py
fastfile/fastfile.py
fastfile.egg-info/PKG-INFO
fastfile.egg-info/SOURCES.txt
fastfile.egg-info/dependency_links.txt
fastfile.egg-info/top_level.txt