Metadata-Version: 2.1
Name: fastfile
Version: 0.0.1
Summary: Writing to files fast.
Home-page: UNKNOWN
Author: Fritz Forster
Author-email: fritzforster@protonmail.com
License: UNKNOWN
Keywords: python,file,write file,fast witing,simple
Platform: UNKNOWN
Classifier: Development Status :: 1 - Planning
Classifier: Intended Audience :: Developers
Classifier: Programming Language :: Python :: 3
Classifier: Operating System :: Unix
Classifier: Operating System :: MacOS :: MacOS X
